src/__init__.py
src/cli_state.py
src/ingl_cli.py
src/instruction.py
src/ledger.py
src/processor.py
src/state.py
src/utils.py
ingl-0.0.511.dist-info/METADATA
ingl-0.0.511.dist-info/WHEEL
ingl-0.0.511.dist-info/entry_points.txt
ingl-0.0.511.dist-info/top_level.txt
ingl-0.0.511.dist-info/RECORD
