Metadata-Version: 2.1
Name: ingl
Version: 0.0.511
Summary: A command line interface for interacting with Ingl-DAO Program Instructions
Home-page: https://www.ingl.io
Author: Ingl-Labs
Author-email: admin@ingl.io
Requires-Dist: click (==8.1.3)
Requires-Dist: asyncclick (==8.1.3.4)
Requires-Dist: solana (==0.29.0)
Requires-Dist: borsh-construct (==0.1.0)
Requires-Dist: base58 (==2.1.1)
Requires-Dist: rich (==13.1.0)
Requires-Dist: ledgerblue (==0.1.43)
